LICENSE.txt
MANIFEST.in
README.md
setup.py
dag_schedule_graph/__init__.py
dag_schedule_graph/dag_schedule.py
dag_schedule_graph/dag_schedule_graph_view.py
dag_schedule_graph/log.py
dag_schedule_graph.egg-info/PKG-INFO
dag_schedule_graph.egg-info/SOURCES.txt
dag_schedule_graph.egg-info/dependency_links.txt
dag_schedule_graph.egg-info/entry_points.txt
dag_schedule_graph.egg-info/requires.txt
dag_schedule_graph.egg-info/top_level.txt
dag_schedule_graph/static/dist/main.js
dag_schedule_graph/static/dist/main.js.LICENSE.txt
dag_schedule_graph/static/js/chart-helper.js
dag_schedule_graph/static/js/index.js
dag_schedule_graph/static/js/__mocks__/randomcolor.js
dag_schedule_graph/static/js/__tests__/chart-helper.test.js
dag_schedule_graph/templates/dag_schedule_graph/index.html
tests/dag_schedule_graph/__init__.py
tests/dag_schedule_graph/test_dag_schedule.py