Metadata-Version: 2.1
Name: dag-schedule-graph
Version: 0.2.0
Summary: Airflow plugin for visualising DAG schedules within 24 hour window of a day.
Home-page: https://github.com/arunvelsriram/dag-schedule-graph
Author: Arunvel Sriram
Author-email: arunvelsriram@gmail.com
License: MIT
Download-URL: https://github.com/arunvelsriram/dag-schedule-graph/archive/v0.2.0.tar.gz
Platform: UNKNOWN
Provides-Extra: dev
